userAgentRandomizer/__init__.py
userAgentRandomizer/assets/Chrome.txt
userAgentRandomizer/assets/Edge.txt
userAgentRandomizer/assets/Firefox.txt
userAgentRandomizer/assets/Opera.txt
userAgentRandomizer/assets/Safari.txt
userAgentRandomizer-0.1.6.dist-info/LICENSE
userAgentRandomizer-0.1.6.dist-info/METADATA
userAgentRandomizer-0.1.6.dist-info/WHEEL
userAgentRandomizer-0.1.6.dist-info/top_level.txt
userAgentRandomizer-0.1.6.dist-info/RECORD
