Metadata-Version: 2.1
Name: userAgentRandomizer
Version: 0.1.6
Summary: Automatically Generate User agents
Home-page: https://github.com/MattWaller/userAgentRandomizer
Author: Matt Waller
Author-email: mattghwaller@gmail.com
License: UNKNOWN
Project-URL: Bug Tracker, https://github.com/MattWaller/userAgentRandomizer/issues
Platform: UNKNOWN
Classifier: Programming Language :: Python :: 3
Classifier: License :: OSI Approved :: MIT License
Classifier: Operating System :: OS Independent
Requires-Python: >=3.6
License-File: LICENSE
